aws_s3_helper/__init__.py
aws_s3_helper/interface.py
aws_s3_helper/s3_base.py
aws_s3_helper/s3_with_logs.py
aws_s3_helper/s3_without_logs.py
aws_s3_helper-1.4.0.dist-info/licenses/LICENSE
aws_s3_helper-1.4.0.dist-info/METADATA
aws_s3_helper-1.4.0.dist-info/WHEEL
aws_s3_helper-1.4.0.dist-info/top_level.txt
aws_s3_helper-1.4.0.dist-info/RECORD
