Metadata-Version: 2.4
Name: aws-s3-helper
Version: 1.4.0
Summary: Abstraction for easy access to AWS S3.
Author-email: Sergio Jimenez Moreno <sergio.jimenez@xauen.io>
License: GNU General Public License v3 (GPLv3)
Project-URL: Homepage, https://github.com/sjm00010/AWS_S3_Helper
Project-URL: Bug Tracker, https://github.com/sjm00010/AWS_S3_Helper/issues
Classifier: Programming Language :: Python :: 3
Classifier: License :: OSI Approved :: GNU General Public License v3 (GPLv3)
Classifier: Operating System :: OS Independent
Requires-Python: >=3.8
License-File: LICENSE
Requires-Dist: boto3==1.38.28
Requires-Dist: tqdm==4.67.1
Dynamic: license-file
